{"last_node_id":5,"last_link_id":5,"nodes":[{"id":1,"type":"PandasLoadCSV","pos":[353.8526611328125,2105.062255859375],"size":[410.5992736816406,95.68482208251953],"flags":{},"order":0,"mode":0,"inputs":[],"outputs":[{"name":"STRING","type":"STRING","links":[2,4],"slot_index":0}],"properties":{"Node name for S&R":"PandasLoadCSV"},"widgets_values":["./custom_nodes/data-analysis/examples/datasets/fruit.csv"]},{"id":3,"type":"PandasSelectColumns","pos":[792.3731079101562,1956.5699462890625],"size":[349.8414306640625,115.1163558959961],"flags":{},"order":1,"mode":0,"inputs":[{"name":"dataframe_json","type":"STRING","link":2,"widget":{"name":"dataframe_json"}}],"outputs":[{"name":"STRING","type":"STRING","links":[3],"slot_index":0}],"properties":{"Node name for S&R":"PandasSelectColumns"},"widgets_values":["","Name, Price"]},{"id":2,"type":"PandasShowDataFrame","pos":[1223.672119140625,1952.651123046875],"size":[323.9862976074219,238.33462524414062],"flags":{},"order":3,"mode":0,"inputs":[{"name":"dataframe_json","type":"STRING","link":3,"widget":{"name":"dataframe_json"}}],"outputs":[{"name":"STRING","type":"STRING","links":null,"shape":6}],"properties":{"Node name for S&R":"PandasShowDataFrame"},"widgets_values":["","             Name  Price\n0             fig   4.11\n1           safou   1.24\n2          papaya   5.11\n3            plum   2.53\n4           guava   0.66\n..            ...    ...\n95  black currant   8.15\n96    red currant   7.71\n97  black currant   4.41\n98    red currant   2.18\n99  black currant   0.80\n\n[100 rows x 2 columns]"]},{"id":4,"type":"PandasSelectRows","pos":[780.7979125976562,2289.15966796875],"size":[390.7399597167969,111.2580337524414],"flags":{},"order":2,"mode":0,"inputs":[{"name":"dataframe_json","type":"STRING","link":4,"widget":{"name":"dataframe_json"}}],"outputs":[{"name":"STRING","type":"STRING","links":[5],"slot_index":0}],"properties":{"Node name for S&R":"PandasSelectRows"},"widgets_values":["","Price < 1"]},{"id":5,"type":"PandasShowDataFrame","pos":[1231.45263671875,2293.01708984375],"size":[301.1099548339844,161.65524291992188],"flags":{},"order":4,"mode":0,"inputs":[{"name":"dataframe_json","type":"STRING","link":5,"widget":{"name":"dataframe_json"}}],"outputs":[{"name":"STRING","type":"STRING","links":null,"shape":6}],"properties":{"Node name for S&R":"PandasShowDataFrame"},"widgets_values":["","             Name  Price  InStock  OnSale\n4           guava   0.66        1       1\n8          pawpaw   0.66        1       1\n17         orange   0.54        0       1\n78         santol   0.79        1       1\n91  black currant   0.51        1       0\n99  black currant   0.80        1       1"]}],"links":[[2,1,0,3,0,"STRING"],[3,3,0,2,0,"STRING"],[4,1,0,4,0,"STRING"],[5,4,0,5,0,"STRING"]],"groups":[],"config":{},"extra":{"ds":{"scale":0.8639278591604511,"offset":[-331.6863902845917,-1872.4571513539743]},"node_versions":{"ComfyUI-Data-Analysis":"235c84b7b8aafc3c4b904ba8f03c89aade96b640"},"ue_links":[]},"version":0.4}